plaster_pastedeploy/__init__.py
plaster_pastedeploy-1.0.1.dist-info/LICENSE.txt
plaster_pastedeploy-1.0.1.dist-info/METADATA
plaster_pastedeploy-1.0.1.dist-info/WHEEL
plaster_pastedeploy-1.0.1.dist-info/entry_points.txt
plaster_pastedeploy-1.0.1.dist-info/top_level.txt
plaster_pastedeploy-1.0.1.dist-info/RECORD
