Metadata-Version: 2.1
Name: plaster-pastedeploy
Version: 1.0.1
Summary: A loader implementing the PasteDeploy syntax to be used by plaster.
Home-page: https://github.com/Pylons/plaster_pastedeploy
Author: Hunter Senft-Grupp
Author-email: pylons-discuss@googlegroups.com
Keywords: plaster,pastedeploy,plaster_pastedeploy,ini,config,egg
Classifier: Development Status :: 5 - Production/Stable
Classifier: Intended Audience :: Developers
Classifier: License :: OSI Approved :: MIT License
Classifier: Natural Language :: English
Classifier: Programming Language :: Python :: 3
Classifier: Programming Language :: Python :: 3.7
Classifier: Programming Language :: Python :: 3.8
Classifier: Programming Language :: Python :: 3.9
Classifier: Programming Language :: Python :: 3.10
Classifier: Programming Language :: Python :: Implementation :: CPython
Classifier: Programming Language :: Python :: Implementation :: PyPy
Requires-Python: >=3.7
Provides-Extra: testing
License-File: LICENSE.txt
